README.md
setup.cfg
setup.py
PSNN/__init__.py
PSNN/model.py
PSNN/server_tools.py
PSNN.egg-info/PKG-INFO
PSNN.egg-info/SOURCES.txt
PSNN.egg-info/dependency_links.txt
PSNN.egg-info/requires.txt
PSNN.egg-info/top_level.txt
PSNN/activation/__init__.py
PSNN/activation/linear.py
PSNN/activation/relu.py
PSNN/activation/sigmoid.py
PSNN/activation/tanh.py
PSNN/layers/__init__.py
PSNN/layers/activation.py
PSNN/layers/concat.py
PSNN/layers/convolve.py
PSNN/layers/dense.py
PSNN/layers/flatten.py
PSNN/layers/recurrent.py
PSNN/layers/reshape.py
PSNN/loss/__init__.py
PSNN/loss/basic.py
bin/PSNN
bin/psnn