Metadata-Version: 2.1
Name: PSNN
Version: 0.1.5
Summary: Python Simple Neural Network - PSNN is python3 lib for machine learning
Home-page: https://github.com/Lukas0025/PSNN
Author: Lukáš Plevač
Author-email: lukasplevac@gmail.com
License: UNKNOWN
Platform: UNKNOWN
Classifier: Programming Language :: Python :: 3
Classifier: License :: OSI Approved :: Apache Software License
Classifier: Operating System :: OS Independent
Requires-Python: >=3.0
